{
  "id": "k4lt-assets",
  "title": "KULT: Divinity Lost · Assets",
  "description": "Assets for KULT: Divinity Lost system.",
  "version": "2.2.0",
  "license": "LICENSE",
  "compatibility": {
    "minimum": "13",
    "verified": "13.342",
    "maximum": "14"
  },
  "authors": [
    {
      "name": "YanK",
      "url": "https://www.buymeacoffee.com/yank",
      "email": "yanklinnomme@gmail.com",
      "discord": "yanklinnomme"
    }
  ],
  "relationships": {
    "systems": [
      {"id": "k4lt"}
    ]
  },
  "esmodules": ["k4lt-assets.js"],
  "packs": [
    {
      "label": "KULT: Divinity Lost · OST",
      "name": "k4lt-ost",
      "type": "Playlist",
      "system": "k4lt",
      "path": "packs/k4lt-ost"
    }
  ],
  "languages": [
    {
      "lang": "en",
      "name": "English",
      "path": "lang/en.json"
    },
    {
      "lang": "fr",
      "name": "Français",
      "path": "lang/fr.json"
    }
  ],
    "url": "https://github.com/YanKlInnomme/FoundryVTT-k4lt-assets",
    "manifest": "",
    "download": ""
}
